snapshot_selenium/__init__.py
snapshot_selenium/_version.py
snapshot_selenium/snapshot.py
snapshot_selenium-0.0.2.dist-info/METADATA
snapshot_selenium-0.0.2.dist-info/WHEEL
snapshot_selenium-0.0.2.dist-info/top_level.txt
snapshot_selenium-0.0.2.dist-info/RECORD
