Metadata-Version: 1.1
Name: snapshot-selenium
Version: 0.0.2
Summary: Render echarts using selenium
Home-page: https://github.com/pyecharts/snapshot-selenium
Author: pyecharts dev team
Author-email: info@pyecharts.com
License: MIT
Download-URL: https://github.com/pyecharts/snapshot-selenium/archive/0.0.2.tar.gz
Keywords: python,pyecharts,chart
Platform: UNKNOWN
Classifier: Topic :: Software Development :: Libraries
Classifier: Programming Language :: Python
Classifier: Intended Audience :: Developers
Classifier: Programming Language :: Python :: 3 :: Only
Classifier: Programming Language :: Python :: 3.5
Classifier: Programming Language :: Python :: 3.6
Classifier: Programming Language :: Python :: 3.7
Classifier: Programming Language :: Python :: 3.8
